{"stat.killEntity.EntityHorse":5,"stat.leaveGame":530,"stat.mineBlock.133":3,"stat.mineBlock.131":1,"stat.mineBlock.134":2,"stat.mineBlock.138":2,"stat.mineBlock.139":2,"stat.killEntity.PigZombie":11,"stat.entityKilledBy.PigZombie":1,"stat.mineBlock.145":2,"stat.mineBlock.146":4,"achievement.diamondsToYou":1,"stat.mineBlock.111":1,"stat.mineBlock.114":3,"stat.killEntity.Enderman":12,"stat.mineBlock.112":68,"stat.mineBlock.113":1,"stat.mineBlock.116":2,"achievement.buildPickaxe":114,"stat.killEntity.Witch":1,"stat.killEntity.Villager":15,"stat.mineBlock.121":192,"stat.mineBlock.126":46,"stat.mineBlock.123":1,"stat.mineBlock.129":1,"achievement.GK1":5,"stat.mineBlock.128":2,"stat.killEntity.EntityBustSkeletonMob":1,"stat.mineBlock.175":129,"defeatedcrow.chalcedony":8,"achievement.killdragon":4,"achievement.primitivemobs.camouflagearmor":4,"achievement.openInventory":9966,"stat.mineBlock.161":325,"stat.mineBlock.162":420,"stat.mineBlock.160":3,"stat.mineBlock.154":8,"stat.mineBlock.153":44,"stat.mineBlock.159":4,"stat.mineBlock.156":8,"stat.deaths":73,"stat.mineBlock.170":46,"stat.mineBlock.171":13,"stat.mineBlock.163":2,"stat.fishCaught":12,"achievement.potion":17,"achievement.primitivemobs.camouflagedye":16,"stat.killEntity.Ghast":3,"achievement.killCow":184,"defeatedcrow.makeTealeaves":32,"achievement.primitivemobs.redcreepsurvive":7,"defeatedcrow.teamaker":1,"achievement.gettingstarted":1,"stat.minecartOneCm":34615,"stat.killEntity.ChocoboYellow":3,"achievement.portal":5,"stat.useItem.6":67,"achievement.acquireIron":96,"stat.useItem.1":1084,"stat.useItem.4":1004,"stat.useItem.5":523,"defeatedcrow.chalGear":2,"stat.useItem.3":4201,"stat.useItem.351":1083,"stat.craftItem.69":39,"stat.useItem.355":28,"stat.useItem.354":1,"stat.useItem.112":8,"stat.useItem.114":21,"stat.useItem.359":108,"stat.useItem.116":3,"stat.craftItem.61":29,"stat.craftItem.65":57,"stat.killEntity.EntityBustZombieMob":13,"stat.useItem.361":62,"stat.useItem.121":58,"stat.useItem.123":3,"stat.useItem.126":111,"stat.craftItem.72":8,"stat.useItem.129":1,"achievement.buildWorkBench":103,"stat.craftItem.76":1,"stat.craftItem.77":3,"stat.useItem.331":85,"stat.useItem.330":10,"stat.craftItem.85":122,"stat.useItem.338":90,"stat.craftItem.89":21,"stat.mineBlock.4":558,"stat.mineBlock.5":149,"stat.mineBlock.3":5548,"stat.mineBlock.1":10875,"stat.craftItem.82":27,"stat.craftItem.80":22,"stat.mineBlock.6":6,"achievement.primitivemobs.treasureslimefriend":2,"stat.flyOneCm":17005765,"stat.useItem.101":195,"stat.useItem.103":9,"stat.craftItem.96":8,"stat.useItem.107":9,"stat.craftItem.95":1120,"stat.useItem.109":26,"stat.craftItem.98":452,"stat.craftItem.91":6,"stat.breakItem.290":2,"stat.killEntity.Bat":8,"stat.craftItem.420":4,"stat.craftItem.29":11,"stat.craftItem.20":2303,"stat.craftItem.22":28,"stat.killEntity.Creeper":12,"stat.useItem.321":43,"stat.useItem.324":7,"stat.useItem.323":105,"cfm.artist":2,"stat.breakItem.285":1,"stat.useItem.328":1,"stat.craftItem.35":8,"stat.craftItem.33":11,"achievement.buildSword":13,"stat.killEntity.Squid":8,"stat.craftItem.47":97,"stat.craftItem.41":84,"stat.craftItem.42":105,"stat.breakItem.275":1,"stat.breakItem.278":1,"stat.breakItem.277":1,"stat.craftItem.44":150,"achievement.killEnemy":1525,"stat.craftItem.58":54,"defeatedcrow.getTeaLeaves":273,"stat.breakItem.261":1,"stat.craftItem.53":28,"stat.craftItem.50":972,"stat.breakItem.267":1,"stat.craftItem.57":24,"stat.craftItem.54":59,"stat.killEntity.Zombie":252,"stat.diveOneCm":2276608,"stat.useItem.65":32,"stat.useItem.66":144,"stat.useItem.61":42,"achievement.buildHoe":13,"stat.breakItem.256":12,"stat.breakItem.258":3,"stat.breakItem.257":38,"achievement.primitivemobs.spiderowner":1,"stat.useItem.69":47,"stat.useItem.76":10,"stat.craftItem.296":360,"stat.useItem.77":2,"stat.craftItem.297":359,"stat.craftItem.298":2,"stat.craftItem.299":1,"stat.jump":80617,"stat.useItem.70":1,"stat.craftItem.290":4,"stat.craftItem.291":2,"stat.craftItem.292":1,"achievement.hee.3542":6,"achievement.hee.3540":13,"achievement.makeBread":678,"achievement.hee.3549":3,"achievement.hee.3548":1,"stat.useItem.79":43,"achievement.hee.3547":8,"stat.useItem.42":104,"stat.useItem.44":160,"stat.useItem.45":10,"stat.useItem.41":115,"cfm.overload":25,"achievement.blazeRod":22,"stat.damageTaken":970252,"stat.useItem.46":763,"stat.useItem.47":67,"stat.useItem.53":35,"stat.useItem.54":79,"stat.useItem.56":24,"stat.useItem.50":1659,"stat.useItem.52":1,"stat.entityKilledBy.Zombie":1,"stat.killEntity.Silverfish":31,"stat.useItem.57":29,"stat.useItem.58":118,"stat.craftItem.261":7,"stat.useItem.20":21,"stat.useItem.153":5,"stat.useItem.152":2,"stat.craftItem.262":33,"stat.craftItem.263":18,"stat.useItem.397":23,"stat.craftItem.264":320,"stat.useItem.154":18,"stat.craftItem.265":980,"stat.craftItem.266":297,"stat.craftItem.267":4,"stat.animalsBred":717,"stat.useItem.159":17,"stat.craftItem.268":1,"stat.craftItem.258":4,"stat.useItem.29":55,"achievement.primitivemobs.lostminerhelp":1,"stat.useItem.24":19,"stat.useItem.162":16,"stat.useItem.27":69,"stat.useItem.164":14,"stat.useItem.163":6,"stat.craftItem.256":18,"stat.craftItem.257":56,"stat.useItem.30":5,"defeatedcrow.craftTart":1,"stat.useItem.39":9,"stat.useItem.35":38,"stat.useItem.38":2,"stat.useItem.372":3,"stat.useItem.133":4,"stat.useItem.379":6,"stat.useItem.138":4,"stat.craftItem.280":1212,"stat.craftItem.281":4,"achievement.hee.3554":1,"stat.mobKills":3744,"stat.useItem.381":9,"stat.useItem.383":61,"stat.craftItem.274":2,"stat.useItem.12":205,"stat.useItem.143":4,"stat.craftItem.276":1,"stat.useItem.146":6,"stat.useItem.145":2,"stat.craftItem.277":4,"stat.craftItem.278":2,"stat.useItem.389":31,"stat.useItem.147":4,"stat.craftItem.279":1,"achievement.enterabyss":4575,"achievement.bookcase":168,"stat.craftItem.270":1,"stat.useItem.17":11,"stat.useItem.391":43,"stat.useItem.13":445,"stat.useItem.390":3,"stat.useItem.392":13,"stat.killEntity.Blaze":3,"achievement.primitivemobs.mimicfake":3,"stat.mineBlock.14":98,"stat.mineBlock.13":623,"stat.mineBlock.16":2012,"stat.mineBlock.15":632,"stat.mineBlock.18":328,"stat.mineBlock.17":286,"stat.mineBlock.12":2859,"achievement.diamonds":111,"achievement.buildBetterPickaxe":114,"achievement.breedCow":198,"stat.killEntity.EntityBustHellDog":8,"cfm.harvester":23,"defeatedcrow.getYuzu":44,"achievement.overkill":7409,"achievement.mineWood":606,"stat.useItem.86":2,"stat.useItem.87":33,"stat.useItem.88":4,"stat.useItem.89":6,"stat.useItem.85":194,"stat.useItem.80":5,"stat.useItem.81":39,"achievement.christmaspillar":8,"stat.useItem.98":619,"achievement.ghast":1,"stat.useItem.95":804,"stat.useItem.96":8,"stat.playOneMinute":10051141,"stat.useItem.401":2,"stat.fallOneCm":2194215,"stat.craftItem.1":1579,"stat.craftItem.400":6,"stat.craftItem.5":2128,"stat.blockChiseled":9919,"stat.craftItem.340":191,"stat.craftItem.101":288,"stat.craftItem.103":9,"stat.craftItem.345":1,"stat.horseOneCm":267895,"stat.craftItem.336":7,"stat.craftItem.339":597,"stat.craftItem.330":1,"stat.swimOneCm":811977,"stat.craftItem.333":3,"stat.climbOneCm":424278,"stat.killEntity.EntityBustEnderman":2,"stat.craftItem.324":9,"stat.craftItem.325":16,"achievement.exploreAllBiomes":{"value":0,"progress":["Sky","Sunflower Plains","Desert M","Roofed Forest","Birch Forest","Extreme Hills M","Darklands Plains","Darklands Mountains","Darklands Forest","Beach","FrozenRiver","Extreme Hills+","River","Ocean","JungleEdge","Taiga","Darklands Highland","Swampland","Birch Forest Hills","Savanna Plateau","ForestHills","Corrupted Land","Flower Forest","Plains","Darklands","TaigaHills","Abyssal Wastelands","DesertHills","Coralium Infested Swamp","Stone Beach","Birch Forest M","Jungle","Forest","JungleHills","Desert","Extreme Hills","Savanna","Hell","Deep Ocean"]},"stat.craftItem.361":56,"stat.craftItem.364":194,"stat.craftItem.123":3,"stat.craftItem.366":44,"stat.craftItem.357":40,"stat.craftItem.116":2,"stat.craftItem.359":5,"stat.craftItem.350":2,"stat.craftItem.351":979,"stat.entityKilledBy.EntityBustEnderman":4,"stat.craftItem.355":19,"stat.craftItem.346":1,"stat.craftItem.107":8,"stat.craftItem.109":12,"achievement.theEnd":9,"stat.craftItem.300":1,"stat.craftItem.301":1,"stat.craftItem.320":20,"stat.craftItem.321":4,"stat.craftItem.323":78,"stat.craftItem.313":6,"achievement.buildFurnace":51,"stat.drop":3685,"stat.craftItem.310":10,"stat.craftItem.311":6,"stat.craftItem.312":12,"stat.killEntity.Sheep":66,"stat.craftItem.306":6,"stat.craftItem.307":4,"stat.craftItem.308":5,"stat.craftItem.309":6,"stat.mineBlock.81":36,"stat.mineBlock.80":30,"stat.mineBlock.82":31,"stat.mineBlock.85":45,"stat.mineBlock.87":1314,"stat.mineBlock.86":77,"stat.mineBlock.89":22,"stat.mineBlock.88":28,"stat.craftItem.173":7,"stat.craftItem.172":35,"stat.mineBlock.95":38,"stat.mineBlock.98":388,"stat.mineBlock.97":4,"stat.mineBlock.69":8,"stat.useItem.295":2281,"stat.boatOneCm":121864,"stat.mineBlock.61":9,"stat.mineBlock.65":1,"stat.mineBlock.67":7,"stat.mineBlock.66":61,"stat.killEntity.EntityBustSpiderMob":2,"stat.killEntity.CaveSpider":19,"stat.mineBlock.79":45,"stat.damageDealt":790859,"stat.mineBlock.70":1,"stat.killEntity.Cow":227,"stat.killEntity.Pig":24,"stat.mineBlock.73":81,"stat.mineBlock.76":4,"stat.mineBlock.78":118,"stat.mineBlock.77":1,"stat.useItem.274":133,"stat.mineBlock.47":32,"stat.mineBlock.46":92,"stat.useItem.276":1097,"stat.mineBlock.49":110,"stat.mineBlock.48":109,"stat.useItem.275":127,"stat.craftItem.143":4,"stat.walkOneCm":61041477,"stat.useItem.278":27156,"stat.craftItem.386":1,"stat.useItem.277":4818,"stat.craftItem.388":108,"stat.playerKills":5,"stat.craftItem.147":4,"stat.useItem.279":977,"stat.craftItem.381":25,"achievement.enchantments":3,"achievement.mineDS":45934,"stat.craftItem.138":1,"stat.mineBlock.41":41,"stat.mineBlock.42":28,"stat.mineBlock.45":8,"stat.mineBlock.44":69,"stat.mineBlock.58":39,"stat.useItem.285":22,"stat.craftItem.371":18,"stat.mineBlock.57":44,"stat.craftItem.374":66,"stat.craftItem.133":5,"stat.craftItem.377":97,"stat.mineBlock.100":284,"stat.mineBlock.103":10,"stat.mineBlock.101":44,"stat.mineBlock.102":1,"stat.mineBlock.50":626,"stat.mineBlock.107":5,"stat.craftItem.126":222,"stat.mineBlock.108":1,"stat.useItem.290":272,"stat.mineBlock.106":19,"stat.mineBlock.54":9,"stat.useItem.292":12,"stat.useItem.291":45,"stat.mineBlock.53":9,"stat.mineBlock.56":76,"stat.mineBlock.109":26,"stat.mineBlock.24":113,"stat.killEntity.Skeleton":177,"stat.mineBlock.27":22,"stat.useItem.256":3884,"stat.mineBlock.29":46,"stat.useItem.258":1237,"stat.useItem.257":12768,"stat.useItem.259":30,"stat.killEntity.Chicken":89,"stat.breakItem.311":5,"stat.breakItem.310":13,"stat.breakItem.313":5,"stat.breakItem.312":4,"stat.killEntity.Spider":54,"stat.breakItem.303":1,"stat.breakItem.306":3,"stat.breakItem.308":3,"stat.breakItem.307":1,"stat.breakItem.309":3,"stat.craftItem.159":24,"achievement.killghoul":10,"stat.mineBlock.21":36,"stat.mineBlock.20":19,"stat.mineBlock.23":1,"stat.mineBlock.22":3,"stat.craftItem.393":186,"stat.mineBlock.35":26,"stat.craftItem.152":7,"stat.mineBlock.38":85,"stat.craftItem.395":1,"stat.mineBlock.37":42,"stat.craftItem.154":10,"stat.useItem.267":437,"stat.craftItem.155":1,"stat.mineBlock.39":10,"stat.useItem.268":48,"stat.craftItem.390":1,"stat.mineBlock.30":284,"achievement.cookFish":2,"stat.useItem.270":11,"stat.mineBlock.32":6,"stat.mineBlock.31":2805}